{
	"name": "df_silver_limpiar_location",
	"properties": {
		"folder": {
			"name": "SILVER"
		},
		"type": "MappingDataFlow",
		"typeProperties": {
			"sources": [
				{
					"dataset": {
						"referenceName": "ds_tabla_location",
						"type": "DatasetReference"
					},
					"name": "source1"
				}
			],
			"sinks": [
				{
					"dataset": {
						"referenceName": "ds_silver_location",
						"type": "DatasetReference"
					},
					"name": "sink1"
				}
			],
			"transformations": [
				{
					"name": "derivedColumn1"
				}
			],
			"scriptLines": [
				"source(output(",
				"          cid as string,",
				"          cntry as string",
				"     ),",
				"     allowSchemaDrift: true,",
				"     validateSchema: false,",
				"     isolationLevel: 'READ_UNCOMMITTED',",
				"     format: 'table') ~> source1",
				"source1 derive(cid = replace(trim(cid), '-', ''),",
				"          cntry = trim(cntry)) ~> derivedColumn1",
				"derivedColumn1 sink(allowSchemaDrift: true,",
				"     validateSchema: false,",
				"     input(",
				"          cid as string,",
				"          cntry as string",
				"     ),",
				"     deletable:false,",
				"     insertable:true,",
				"     updateable:false,",
				"     upsertable:false,",
				"     format: 'table',",
				"     skipDuplicateMapInputs: true,",
				"     skipDuplicateMapOutputs: true,",
				"     errorHandlingOption: 'stopOnFirstError',",
				"     mapColumn(",
				"          cid,",
				"          cntry",
				"     )) ~> sink1"
			]
		}
	}
}